intersect/__init__.py
intersect/intersect.py
intersect-1.3.2.dist-info/licenses/LICENSE
intersect-1.3.2.dist-info/METADATA
intersect-1.3.2.dist-info/WHEEL
intersect-1.3.2.dist-info/top_level.txt
intersect-1.3.2.dist-info/RECORD
